commitloom/__init__.py
commitloom/__main__.py
commitloom/cli/__init__.py
commitloom/cli/cli_handler.py
commitloom/cli/console.py
commitloom/config/__init__.py
commitloom/config/settings.py
commitloom/core/__init__.py
commitloom/core/analyzer.py
commitloom/core/batch.py
commitloom/core/git.py
commitloom/core/smart_grouping.py
commitloom/services/__init__.py
commitloom/services/ai_service.py
commitloom/services/metrics.py
commitloom-1.6.4.dist-info/METADATA
commitloom-1.6.4.dist-info/WHEEL
commitloom-1.6.4.dist-info/entry_points.txt
commitloom-1.6.4.dist-info/licenses/LICENSE
commitloom-1.6.4.dist-info/RECORD
