Metadata-Version: 2.4
Name: commitloom
Version: 1.6.4
Summary: Weave perfect git commits with AI-powered intelligence
Project-URL: Homepage, https://github.com/Arakiss/commitloom
Project-URL: Repository, https://github.com/Arakiss/commitloom
Project-URL: Documentation, https://github.com/Arakiss/commitloom#readme
Project-URL: Bug Tracker, https://github.com/Arakiss/commitloom/issues
Author-email: Petru Arakiss <petruarakiss@gmail.com>
License: MIT
License-File: LICENSE
Keywords: ai,cli,commit,git,git-tools,openai,semantic-commits
Classifier: Development Status :: 4 - Beta
Classifier: Environment :: Console
Classifier: Intended Audience :: Developers
Classifier: License :: OSI Approved :: MIT License
Classifier: Operating System :: OS Independent
Classifier: Programming Language :: Python :: 3
Classifier: Programming Language :: Python :: 3.10
Classifier: Programming Language :: Python :: 3.11
Classifier: Programming Language :: Python :: 3.12
Classifier: Topic :: Software Development :: Version Control :: Git
Classifier: Typing :: Typed
Requires-Python: >=3.10
Requires-Dist: click>=8.1.7
Requires-Dist: python-dotenv>=1.0.1
Requires-Dist: requests>=2.32.3
Requires-Dist: rich>=13.9.4
